zylogger/__init__.py
zylogger-0.0.1.dist-info/LICENSE
zylogger-0.0.1.dist-info/METADATA
zylogger-0.0.1.dist-info/WHEEL
zylogger-0.0.1.dist-info/top_level.txt
zylogger-0.0.1.dist-info/RECORD
