Metadata-Version: 2.1
Name: zylogger
Version: 0.0.1
Summary: A logger can be used directly
Home-page: https://github.com/nicolerobin/zylogger
Author: robin zhang
Author-email: lit050528@gmail.com
License: UNKNOWN
Platform: UNKNOWN
Requires-Python: >=2.7
